setup.py
Pry_Lexer.egg-info/PKG-INFO
Pry_Lexer.egg-info/SOURCES.txt
Pry_Lexer.egg-info/dependency_links.txt
Pry_Lexer.egg-info/entry_points.txt
Pry_Lexer.egg-info/top_level.txt
pry_lexer/__init__.py
pry_lexer.egg-info/SOURCES.txt