Metadata-Version: 1.0
Name: pry-lexer
Version: 0.1.2
Summary: A pygments lexer for pry sessions
Home-page: https://github.com/ConradIrwin/pry-lexer
Author: Conrad Irwin
Author-email: me@cirw.in
License: UNKNOWN
Platform: UNKNOWN
